AUTHORS.rst
CONTRIBUTING.rst
HISTORY.rst
LICENSE
MANIFEST.in
README.rst
setup.cfg
setup.py
docs/Makefile
docs/authors.rst
docs/conf.py
docs/contributing.rst
docs/history.rst
docs/index.rst
docs/installation.rst
docs/make.bat
docs/readme.rst
docs/usage.rst
tests/__init__.py
tests/test_visearch.py
tests/fixtures/images.json
tests/fixtures/notimage.pdf
tests/fixtures/upload.jpg
visearch/__init__.py
visearch/bind.py
visearch/client.py
visearch.egg-info/PKG-INFO
visearch.egg-info/SOURCES.txt
visearch.egg-info/dependency_links.txt
visearch.egg-info/not-zip-safe
visearch.egg-info/requires.txt
visearch.egg-info/top_level.txt