Metadata-Version: 2.1
Name: visearch
Version: 0.5.0
Summary: ViSearch Python SDK
Home-page: https://github.com/visenze/visearch-sdk-python
Author: Dejun
Author-email: dejun@visenze.com
License: BSD
Keywords: visearch
Platform: UNKNOWN
Classifier: Development Status :: 2 - Pre-Alpha
Classifier: Intended Audience :: Developers
Classifier: License :: OSI Approved :: BSD License
Classifier: Natural Language :: English
Classifier: Programming Language :: Python :: 2
Classifier: Programming Language :: Python :: 2.7
Classifier: Programming Language :: Python :: 3
Classifier: Programming Language :: Python :: 3.3
Classifier: Programming Language :: Python :: 3.4
